gym_simplifiedtetris_AVELA/__init__.py
gym_simplifiedtetris_AVELA/register.py
gym_simplifiedtetris_AVELA/agents/__init__.py
gym_simplifiedtetris_AVELA/agents/base.py
gym_simplifiedtetris_AVELA/agents/dellacherie.py
gym_simplifiedtetris_AVELA/agents/q_learning.py
gym_simplifiedtetris_AVELA/agents/uniform.py
gym_simplifiedtetris_AVELA/auxiliary/__init__.py
gym_simplifiedtetris_AVELA/auxiliary/colours.py
gym_simplifiedtetris_AVELA/auxiliary/polymino.py
gym_simplifiedtetris_AVELA/envs/__init__.py
gym_simplifiedtetris_AVELA/envs/_simplified_tetris_base_env.py
gym_simplifiedtetris_AVELA/envs/_simplified_tetris_engine.py
gym_simplifiedtetris_AVELA/envs/simplified_tetris_AVELA_env.py
gym_simplifiedtetris_AVELA/envs/simplified_tetris_binary_env.py
gym_simplifiedtetris_AVELA/envs/simplified_tetris_heights_env.py
gym_simplifiedtetris_AVELA/envs/simplified_tetris_part_binary_env.py
gym_simplifiedtetris_AVELA/envs/reward_shaping/__init__.py
gym_simplifiedtetris_AVELA/envs/reward_shaping/_potential_based_shaping_reward.py
gym_simplifiedtetris_AVELA/envs/reward_shaping/simplified_tetris_binary_shaped_env.py
gym_simplifiedtetris_AVELA/envs/reward_shaping/simplified_tetris_heights_shaped_env.py
gym_simplifiedtetris_AVELA/envs/reward_shaping/simplified_tetris_part_binary_shaped_env.py
gym_simplifiedtetris_AVELA-0.2.1.dist-info/LICENSE.md
gym_simplifiedtetris_AVELA-0.2.1.dist-info/METADATA
gym_simplifiedtetris_AVELA-0.2.1.dist-info/WHEEL
gym_simplifiedtetris_AVELA-0.2.1.dist-info/top_level.txt
gym_simplifiedtetris_AVELA-0.2.1.dist-info/RECORD
