Metadata-Version: 2.1
Name: gym-simplifiedtetris-AVELA
Version: 0.2.1
Summary: A small example package
Home-page: https://github.com/pypa/sampleproject
Author: arroyv
Author-email: avelauw@guw.edu
Project-URL: Bug Tracker, https://github.com/pypa/sampleproject/issues
Classifier: Programming Language :: Python :: 3
Classifier: License :: OSI Approved :: MIT License
Classifier: Operating System :: OS Independent
Requires-Python: >=3.6
License-File: LICENSE.md
